uniswap_viewer/__init__.py
uniswap_viewer/utils.py
uniswap_viewer/viewer_async.py
uniswap_viewer/viewer_sync.py
uniswap_viewer/source/erc20-abi.json
uniswap_viewer/source/factory-abi.json
uniswap_viewer/source/pool-abi.json
uniswap_viewer-0.1.9.dist-info/METADATA
uniswap_viewer-0.1.9.dist-info/WHEEL
uniswap_viewer-0.1.9.dist-info/top_level.txt
uniswap_viewer-0.1.9.dist-info/RECORD
