Metadata-Version: 2.4
Name: uniswap-viewer
Version: 0.1.9
Summary: Lightweight Python library for reading Uniswap V3 prices and tick data via Web3.
Home-page: https://github.com/fomalhaut88/uniswap-viewer
Author: Alexander Fomalhaut
License: MIT
Keywords: uniswap v3 web3 defi ethereum blockchain async
Classifier: Development Status :: 3 - Alpha
Classifier: Intended Audience :: Developers
Classifier: Topic :: Software Development :: Libraries
Classifier: Topic :: Internet :: WWW/HTTP
Classifier: License :: OSI Approved :: MIT License
Classifier: Programming Language :: Python :: 3
Classifier: Programming Language :: Python :: 3.8
Classifier: Programming Language :: Python :: 3.9
Classifier: Programming Language :: Python :: 3.10
Classifier: Programming Language :: Python :: 3.11
Classifier: Programming Language :: Python :: 3.12
Requires-Python: >=3.8
Requires-Dist: web3>=7.11
Dynamic: author
Dynamic: classifier
Dynamic: description
Dynamic: description-content-type
Dynamic: home-page
Dynamic: keywords
Dynamic: license
Dynamic: requires-dist
Dynamic: requires-python
Dynamic: summary
